lab2ai/__init__.py
lab2ai/app.py
lab2ai/models/CustomPrint.py
lab2ai-0.0.1.dist-info/entry_points.txt
lab2ai-0.0.1.dist-info/METADATA
lab2ai-0.0.1.dist-info/WHEEL
lab2ai-0.0.1.dist-info/RECORD
