Metadata-Version: 2.3
Name: lab2ai
Version: 0.0.1
Summary: Auxiliary tools for Rankadmet
Author: Julio Cesar Xavier
Author-email: jcaxavier2@gmail.com
Requires-Python: >=3.10,<4.0
Classifier: Programming Language :: Python :: 3
Classifier: Programming Language :: Python :: 3.10
Classifier: Programming Language :: Python :: 3.11
Classifier: Programming Language :: Python :: 3.12
Classifier: Programming Language :: Python :: 3.13
Requires-Dist: XlsxWriter (>=3.2.0,<4.0.0)
Requires-Dist: openbabel-wheel (==3.1.1.22)
Requires-Dist: rich (>=13.9.3,<14.0.0)
